o_nakala_core/__init__.py
o_nakala_core/autonomous_generator.py
o_nakala_core/collaborative_intelligence.py
o_nakala_core/collection.py
o_nakala_core/curator.py
o_nakala_core/ml_engine.py
o_nakala_core/predictive_analytics.py
o_nakala_core/prepopulation.py
o_nakala_core/relationships.py
o_nakala_core/templates.py
o_nakala_core/upload.py
o_nakala_core/user_info.py
o_nakala_core/vocabulary.py
o_nakala_core/auth/__init__.py
o_nakala_core/auth/auth_middleware.py
o_nakala_core/auth/institutional_auth.py
o_nakala_core/auth/session_manager.py
o_nakala_core/auth/sso_provider.py
o_nakala_core/auth/user_manager.py
o_nakala_core/cli/__init__.py
o_nakala_core/cli/collection.py
o_nakala_core/cli/curator.py
o_nakala_core/cli/preview.py
o_nakala_core/cli/upload.py
o_nakala_core/cli/user_info.py
o_nakala_core/common/__init__.py
o_nakala_core/common/config.py
o_nakala_core/common/exceptions.py
o_nakala_core/common/utils.py
o_nakala_core-2.5.1.dist-info/licenses/LICENSE
o_nakala_core-2.5.1.dist-info/METADATA
o_nakala_core-2.5.1.dist-info/WHEEL
o_nakala_core-2.5.1.dist-info/entry_points.txt
o_nakala_core-2.5.1.dist-info/top_level.txt
o_nakala_core-2.5.1.dist-info/RECORD
