Metadata-Version: 2.4
Name: o-nakala-core
Version: 2.5.1
Summary: A comprehensive Python library and CLI toolkit for the NAKALA research data repository, designed for digital humanities workflows
Author: xy-liao
License-Expression: MIT
Project-URL: Homepage, https://nakala.fr
Project-URL: Repository, https://github.com/xy-liao/o-nakala-core
Project-URL: Documentation, https://nakala.fr/documentation
Project-URL: Bug Tracker, https://github.com/xy-liao/o-nakala-core/issues
Keywords: nakala,research-data,repository,api-client,digital-humanities,metadata,cli,academic
Classifier: Development Status :: 5 - Production/Stable
Classifier: Intended Audience :: Science/Research
Classifier: Operating System :: OS Independent
Classifier: Programming Language :: Python :: 3
Classifier: Programming Language :: Python :: 3.9
Classifier: Programming Language :: Python :: 3.10
Classifier: Programming Language :: Python :: 3.11
Classifier: Programming Language :: Python :: 3.12
Classifier: Topic :: Internet :: WWW/HTTP :: Dynamic Content
Classifier: Topic :: Software Development :: Libraries :: Python Modules
Classifier: Topic :: Scientific/Engineering :: Information Analysis
Classifier: Topic :: Database
Classifier: Topic :: Text Processing
Requires-Python: >=3.9
License-File: LICENSE
Requires-Dist: requests>=2.32.3
Requires-Dist: tenacity>=9.1.2
Requires-Dist: typing-extensions>=4.14.0
Provides-Extra: dev
Requires-Dist: pytest>=7.0.0; extra == "dev"
Requires-Dist: pytest-cov>=4.0.0; extra == "dev"
Requires-Dist: black>=22.0.0; extra == "dev"
Requires-Dist: flake8>=5.0.0; extra == "dev"
Requires-Dist: mypy>=1.0.0; extra == "dev"
Provides-Extra: cli
Requires-Dist: click>=8.0.0; extra == "cli"
Requires-Dist: rich>=13.0.0; extra == "cli"
Requires-Dist: python-dotenv>=1.0.0; extra == "cli"
Provides-Extra: ml
Requires-Dist: numpy>=1.21.0; extra == "ml"
Requires-Dist: scikit-learn>=1.0.0; extra == "ml"
Provides-Extra: all
Requires-Dist: o-nakala-core[cli,dev,ml]; extra == "all"
Dynamic: license-file
